py_fastapi_logging/__init__.py
py_fastapi_logging/aiohttp.py
py_fastapi_logging/aiopika.py
py_fastapi_logging/config/__init__.py
py_fastapi_logging/config/config.py
py_fastapi_logging/constants.py
py_fastapi_logging/data_filter.py
py_fastapi_logging/formatters/__init__.py
py_fastapi_logging/formatters/base.py
py_fastapi_logging/formatters/json.py
py_fastapi_logging/formatters/simple.py
py_fastapi_logging/middlewares/__init__.py
py_fastapi_logging/middlewares/logging.py
py_fastapi_logging/middlewares/utils/__init__.py
py_fastapi_logging/middlewares/utils/request_id.py
py_fastapi_logging/py.typed
py_fastapi_logging/schemas/__init__.py
py_fastapi_logging/schemas/base.py
py_fastapi_logging/schemas/request.py
py_fastapi_logging/schemas/response.py
py_fastapi_logging/utils/__init__.py
py_fastapi_logging/utils/extra.py
py_fastapi_logging/utils/parse_header.py
py_fastapi_logging-0.7.0.dist-info/LICENSE
py_fastapi_logging-0.7.0.dist-info/METADATA
py_fastapi_logging-0.7.0.dist-info/WHEEL
py_fastapi_logging-0.7.0.dist-info/RECORD
