Metadata-Version: 2.3
Name: py-fastapi-logging
Version: 0.7.0
Summary: FastAPI Logging
License: MIT
Keywords: fastapi,logging,middleware
Author: RockITSoft
Requires-Python: >=3.10,<4.0
Classifier: License :: OSI Approved :: MIT License
Classifier: Programming Language :: Python :: 3
Classifier: Programming Language :: Python :: 3.10
Classifier: Programming Language :: Python :: 3.11
Classifier: Programming Language :: Python :: 3.12
Classifier: Programming Language :: Python :: 3.13
Provides-Extra: aiohttp
Provides-Extra: aiopika
Provides-Extra: all
Requires-Dist: aio-pika (>=6) ; extra == "all" or extra == "aiopika"
Requires-Dist: aiohttp (>=3) ; extra == "all" or extra == "aiohttp"
Requires-Dist: fastapi (>=0.70.1)
